{
    "format_version": "1.13.0",
    "minecraft:structure_template_feature": {
        "description": {
            "identifier": "mst:house_feature"
        },
        "structure_name": "mst:house", 
        "adjustment_radius": 12,
        "facing_direction": "random",
        "constraints": {
            "grounded": {},
            "unburied": {},
"block_intersection": {
    "block_allowlist": [
        "minecraft:air",
        "minecraft:dirt",
        "minecraft:grass_block"
    ]
}

        }
    }
}
