{
  "format_version": "1.21.0",
  "minecraft:entity": {
    "description": {
      "identifier": "kingdoms:military_transport",
      "is_spawnable": false,
      "is_summonable": true,
      "is_experimental": false
    },
    "components": {
      "minecraft:type_family": { "family": ["kingdoms_cart", "inanimate"] },
      "minecraft:collision_box": { "width": 1.0, "height": 1.2 },
      "minecraft:health": { "value": 40, "max": 40 },
      "minecraft:movement": { "value": 0.18 },
      "minecraft:navigation.walk": {
        "can_path_over_water": false,
        "avoid_water": true,
        "avoid_damage_blocks": false
      },
      "minecraft:movement.basic": {},
      "minecraft:physics": {},
      "minecraft:pushable": { "is_pushable": false },
      "minecraft:nameable": {},
      "minecraft:loot": { "table": "loot_tables/entities/trade_cart.json" }
    }
  }
}
